{
  "code-organization-judge": "Evaluates file and folder structure organization from implementation plans",
  "test-judge": "Evaluates test content quality including coverage, assertions, structure, and best practices",
  "custom-best-practices-judge": "Evaluates code implementation adherence to custom best practices documents",
  "verbosity-judge": "Evaluates whether implementation plan verbosity is appropriately calibrated to problem complexity",
  "solid-isp-dip-judge": "Evaluates code implementation adherence to SOLID Interface Segregation Principle (ISP) and Dependency Inversion Principle (DIP)",
  "goal-alignment-judge": "Evaluates whether an implementation plan addresses the core business/functional goals expressed in the PRD",
  "readability-judge": "Evaluates implementation plan readability with focus on clarity, structure, and template adherence",
  "ssot-judge": "Evaluates implementation plans for SSOT (Single Source of Truth) violations",
  "technical-accuracy-judge": "Evaluates technical accuracy of AI assistant responses including API usage, language features, and algorithmic concepts",
  "dry-judge": "Evaluates implementation plans for DRY (Don't Repeat Yourself) violations",
  "kiss-judge": "Evaluates implementation plans for KISS (Keep It Simple) violations",
  "solid-open-closed-judge": "Evaluates code implementation adherence to SOLID Open/Closed Principle (OCP)",
  "solid-liskov-substitution-judge": "Evaluates code implementation adherence to SOLID Liskov Substitution Principle (LSP)"
}
